{
 "12": {
  "editions": [
   1,
   2
  ],
  "active": false,
  "count": 3,
  "best": 4,
  "active_in": 2
 },
 "17": {
  "editions": [
   1,
   2
  ],
  "active": false,
  "count": 3,
  "best": 2,
  "active_in": 2
 },
 "18": {
  "editions": [
   1,
   2
  ],
  "active": false,
  "count": 3,
  "best": 1,
  "active_in": 2
 },
 "19": {
  "editions": [
   1,
   2
  ],
  "active": false,
  "count": 3,
  "best": 6,
  "active_in": 2
 },
 "20": {
  "editions": [
   1,
   2
  ],
  "active": false,
  "count": 3,
  "best": 3,
  "active_in": 2
 },
 "117": {
  "editions": [
   1,
   2
  ],
  "active": false,
  "count": 3,
  "best": 9,
  "active_in": 2
 },
 "120": {
  "editions": [
   1,
   2
  ],
  "active": false,
  "count": 3,
  "best": 5,
  "active_in": 2
 },
 "125": {
  "editions": [
   1,
   2
  ],
  "active": false,
  "count": 3,
  "best": 3,
  "active_in": 2
 },
 "127": {
  "editions": [
   1,
   2
  ],
  "active": false,
  "count": 3,
  "best": 13,
  "active_in": 2
 },
 "130": {
  "editions": [
   2
  ],
  "active": false,
  "count": 2,
  "best": 3,
  "active_in": 2
 },
 "135": {
  "editions": [
   2
  ],
  "active": false,
  "count": 1,
  "best": 8,
  "active_in": 2
 },
 "141": {
  "editions": [
   1
  ],
  "active": false,
  "count": 1,
  "best": 12,
  "active_in": 1
 },
 "153": {
  "editions": [
   2
  ],
  "active": false,
  "count": 2,
  "best": 12,
  "active_in": 2
 },
 "174": {
  "editions": [
   1,
   2
  ],
  "active": false,
  "count": 3,
  "best": 5,
  "active_in": 2
 },
 "176": {
  "editions": [
   2
  ],
  "active": false,
  "count": 2,
  "best": 10,
  "active_in": 2
 },
 "190": {
  "editions": [
   1,
   2
  ],
  "active": false,
  "count": 3,
  "best": 1,
  "active_in": 2
 },
 "195": {
  "editions": [
   1,
   2
  ],
  "active": false,
  "count": 3,
  "best": 2,
  "active_in": 2
 },
 "295": {
  "editions": [
   1,
   2
  ],
  "active": false,
  "count": 3,
  "best": 1,
  "active_in": 2
 },
 "326": {
  "editions": [
   2
  ],
  "active": false,
  "count": 1,
  "best": 19,
  "active_in": 2
 },
 "770": {
  "editions": [
   2
  ],
  "active": false,
  "count": 1,
  "best": 6,
  "active_in": 2
 }
}